{
"cultos": [
    {
      "id": 1,
      "ativo": "true",
      "ano": 2024,
      "nome": "Abertura Pentecostes",
      "descricao": "Mensagem: O Poder Sobrenatural do Jejum",
      "localEvento": "IC Colina",
      "periodoEvento": "05 de Maio - 4 cultos",
      "mesReferencia" : "Maio",
      "musicas": [
        {
          "numeroCena": 1,
          "cena": "ABERTURA",
          "nomeMusica": "PRAISE",
          "linkMusica": "https://www.dropbox.com/scl/fo/d1b1a6uaz2tl1hcy18cpw/AIkmxJTRdqtgA7W3kfnvvTI?rlkey=xlrcpguk0slu95wiqlp626w3j&st=ajn7zbmu&dl=0",
          "anotacao": "TOM A",
          "status": "OK"
        },
        {
          "numeroCena": 2,
          "cena": "",
          "nomeMusica": "ANOTHER IN THE FIRE",
          "linkMusica": "https://www.dropbox.com/scl/fo/erl1zunyxmmvy47u8kghw/h?rlkey=l4wv7of3vfwp8rcgmxtnohl4f&dl=0",
          "anotacao": "AUTO 2024",
          "status": "OK"
        },
        {
          "numeroCena": 3,
          "cena": "",
          "nomeMusica": "SANTO ( HOLY 2024 )",
          "linkMusica": "https://www.dropbox.com/scl/fo/y4dvr850ahvmphb09olzr/h?rlkey=nzzb8dzlquno923bouvl1v1ec&dl=0",
          "anotacao": "------",
          "status": "OK"
        },
        {
          "numeroCena": 4,
          "cena": "INTERCESSÃO",
          "nomeMusica": "MIRACLES",
          "linkMusica": "https://www.dropbox.com/scl/fo/jsh2vzknztghicjydsae5/h?rlkey=6g2gsnho0xsh0ybbhsdgk0ebi&dl=0",
          "anotacao": "------",
          "status": "OK"
        },
        {
          "numeroCena": 5,
          "cena": "DÍZIMOS",
          "nomeMusica": "HE HEIGNS ( NEWBOYS )",
          "linkMusica": "https://www.dropbox.com/scl/fo/uvxu07dk0vmrkhtm4vtvb/h?rlkey=xanf5nuqfakv4bgo7tll86jj5&dl=0",
          "anotacao": "Repete 2x, na 3ª TACET, na 4ª vez segue pro final",
          "status": "OK"
        },
        {
          "numeroCena": 6,
          "cena": "CEIA DO SENHOR",
          "nomeMusica": "ARMS OF GRACE ( TOM D )",
          "linkMusica": "https://www.dropbox.com/scl/fo/b0r2uok81cloyp4ys3am9/h?rlkey=7xsmvz9dweoajfgewcw6uii99&dl=0",
          "anotacao": "Tom em D",
          "status": "OK"
        },
        {
          "numeroCena": 7,
          "cena": "ESPECIAL",
          "nomeMusica": "LET MY SOUL ( GATEWAY )",
          "linkMusica": "https://www.dropbox.com/scl/fo/lukpn54bj97lfw86ovvav/h?rlkey=98ztk6qst16d1ym1wegkmjrbi&dl=0",
          "anotacao": "TOCAR APENAS 2 COMPASSOS DA INTRODUÇÃO ",
          "status": "OK"
        }
      ]
    },
    {
      "id": 2,
      "ativo: true,
      "ano": 2024,
      "nome": "CIDADE CONFERENCE",
      "descricao": "Abertura da CIDADE CONFERENCE",
      "localEvento": "IC Colina",
      "periodoEvento": "30 de Maio - Abertura",
      "mesReferencia": "Maio",
      "musicas": [
        {
          "numeroCena": 1,
          "cena": "ABERTURA",
          "nomeMusica": "The God Who Sees",
          "linkMusica": "#",
          "anotacao": "",
          "status": "OK"
        }
      ]
    }
  ]
}
